{
    "2019-01-12": {
        "date": "2019-01-12",
        "questions": 5,
        "correct": 0,
        "wrong": 5,
        "spent_time": 0,
        "faults": []
    },
    "2019-01-13": {
        "date": "2019-01-13",
        "questions": 30,
        "correct": 18,
        "wrong": 9,
        "spent_time": 0,
        "faults": []
    },
    "2019-01-14": {
        "date": "2019-01-14",
        "questions": 50,
        "correct": 19,
        "wrong": 30,
        "spent_time": 0,
        "faults": []
    },
    "2019-01-15": {
        "date": "2019-01-15",
        "questions": 30,
        "correct": 13,
        "wrong": 15,
        "spent_time": 0,
        "faults": []
    },
    "2019-01-16": {
        "date": "2019-01-16",
        "questions": 30,
        "correct": 11,
        "wrong": 19,
        "spent_time": 0,
        "faults": []
    },
    "2019-01-17": {
        "date": "2019-01-17",
        "questions": 100,
        "correct": 46,
        "wrong": 54,
        "spent_time": 0,
        "faults": []
    },
    "2019-01-18": {
        "date": "2019-01-18",
        "questions": 100,
        "correct": 42,
        "wrong": 58,
        "spent_time": 0,
        "faults": []
    },
    "2019-01-19": {
        "date": "2019-01-19",
        "questions": 100,
        "correct": 50,
        "wrong": 50,
        "spent_time": 0,
        "faults": []
    },
    "2019-01-20": {
        "date": "2019-01-20",
        "questions": 50,
        "correct": 22,
        "wrong": 28,
        "spent_time": 0,
        "faults": []
    },
    "2019-01-21": {
        "date": "2019-01-21",
        "questions": 50,
        "correct": 15,
        "wrong": 35,
        "spent_time": 0,
        "faults": []
    },
    "2019-01-22": {
        "date": "2019-01-22",
        "questions": 50,
        "correct": 33,
        "wrong": 13,
        "spent_time": 0,
        "faults": []
    },
    "2019-01-23": {
        "date": "2019-01-23",
        "questions": 50,
        "correct": 44,
        "wrong": 6,
        "spent_time": 0,
        "faults": []
    },
    "2019-01-24": {
        "date": "2019-01-24",
        "questions": 50,
        "correct": 24,
        "wrong": 26,
        "spent_time": 0,
        "faults": []
    },
    "2019-01-25": {
        "date": "2019-01-25",
        "questions": 53,
        "correct": 37,
        "wrong": 15,
        "spent_time": 0,
        "faults": []
    },
    "2019-01-26": {
        "date": "2019-01-26",
        "questions": 50,
        "correct": 37,
        "wrong": 13,
        "spent_time": 740,
        "faults": [
            256,
            225,
            166,
            135,
            295,
            168,
            237,
            240,
            208,
            242,
            211,
            249,
            126
        ]
    },
    "2019-01-27": {
        "date": "2019-01-27",
        "questions": 50,
        "correct": 38,
        "wrong": 12,
        "spent_time": 723,
        "faults": [
            160,
            161,
            227,
            44,
            77,
            142,
            177,
            242,
            49,
            89,
            27,
            158
        ]
    },
    "2019-01-28": {
        "date": "2019-01-28",
        "questions": 50,
        "correct": 35,
        "wrong": 15,
        "spent_time": 626,
        "faults": [
            259,
            293,
            296,
            298,
            299,
            44,
            13,
            177,
            18,
            19,
            276,
            245,
            88,
            26,
            31
        ]
    },
    "2019-01-29": {
        "date": "2019-01-29",
        "questions": 50,
        "correct": 37,
        "wrong": 13,
        "spent_time": 762,
        "faults": [
            289,
            194,
            33,
            228,
            292,
            262,
            7,
            230,
            265,
            22,
            184,
            251,
            287
        ]
    },
    "2019-01-30": {
        "date": "2019-01-30",
        "questions": 50,
        "correct": 21,
        "wrong": 29,
        "spent_time": 887,
        "faults": [
            321,
            322,
            323,
            324,
            301,
            302,
            303,
            304,
            307,
            309,
            310,
            312,
            313,
            314,
            316,
            318,
            319
        ]
    },
    "2019-01-31": {
        "date": "2019-01-31",
        "questions": 50,
        "correct": 22,
        "wrong": 28,
        "spent_time": 1022,
        "faults": [
            302,
            310,
            314,
            326,
            327,
            328,
            329,
            331,
            332,
            334,
            335,
            336,
            337,
            338,
            339,
            340,
            341,
            342,
            344,
            345
        ]
    },
    "2019-02-01": {
        "date": "2019-02-01",
        "questions": 50,
        "correct": 38,
        "wrong": 12,
        "spent_time": 800,
        "faults": [
            96,
            328,
            234,
            45,
            338,
            276,
            310,
            343,
            280,
            284,
            253,
            158
        ]
    },
    "2019-02-02": {
        "date": "2019-02-02",
        "questions": 50,
        "correct": 34,
        "wrong": 16,
        "spent_time": 1082,
        "faults": [
            352,
            353,
            354,
            355,
            356,
            262,
            346,
            303,
            178,
            244,
            253,
            218,
            347,
            317,
            350
        ]
    },
    "2019-02-03": {
        "date": "2019-02-03",
        "questions": 51,
        "correct": 33,
        "wrong": 18,
        "spent_time": 955,
        "faults": [
            320,
            358,
            360,
            361,
            362,
            363,
            43,
            365,
            366,
            303,
            48,
            207,
            143,
            339,
            345
        ]
    },
    "2019-02-04": {
        "date": "2019-02-04",
        "questions": 50,
        "correct": 34,
        "wrong": 16,
        "spent_time": 978,
        "faults": [
            9,
            367,
            368,
            369,
            370,
            371,
            372,
            373,
            374,
            375,
            344,
            377,
            283
        ]
    },
    "2019-02-05": {
        "date": "2019-02-05",
        "questions": 50,
        "correct": 37,
        "wrong": 13,
        "spent_time": 778,
        "faults": [
            382,
            5,
            261,
            365,
            366,
            239,
            181,
            22,
            57,
            315,
            252,
            157,
            254
        ]
    }
}